odoo/addons/ssh/LICENSE
odoo/addons/ssh/README.rst
odoo/addons/ssh/__init__.py
odoo/addons/ssh/__manifest__.py
odoo/addons/ssh/images/screen.png
odoo/addons/ssh/models/__init__.py
odoo/addons/ssh/models/res_company.py
odoo/addons/ssh/models/res_config_settings.py
odoo/addons/ssh/models/res_users.py
odoo/addons/ssh/models/res_users_keychain.py
odoo/addons/ssh/static/description/icon.png
odoo/addons/ssh/static/description/index.html
odoo/addons/ssh/tests/__init__.py
odoo/addons/ssh/tests/test_res_users_keychain.py
odoo/addons/ssh/views/res_config_settings_view.xml
odoo/addons/ssh/views/res_users_views.xml
odoo_addon_ssh-18.0.1.0.0.dist-info/METADATA
odoo_addon_ssh-18.0.1.0.0.dist-info/WHEEL
odoo_addon_ssh-18.0.1.0.0.dist-info/top_level.txt
odoo_addon_ssh-18.0.1.0.0.dist-info/RECORD
